picozero/__init__.py
picozero/picozero.py
picozero-0.5.0.dist-info/licenses/LICENSE.md
picozero-0.5.0.dist-info/METADATA
picozero-0.5.0.dist-info/WHEEL
picozero-0.5.0.dist-info/top_level.txt
picozero-0.5.0.dist-info/RECORD
